interval_service/__init__.py
interval_service-0.0.0.dist-info/METADATA
interval_service-0.0.0.dist-info/WHEEL
interval_service-0.0.0.dist-info/top_level.txt
interval_service-0.0.0.dist-info/RECORD
