Metadata-Version: 2.1
Name: interval-service
Version: 0.0.0
Summary: Coming soon
Author-email: Simon Patton <sjpatton@lbl.gov>
